deailab/__init__.py
deailab/_version.py
deailab/deai_handler.py
deailab/handlers.py
deailab/job_manager.py
deailab/tools.py
deailab/tests/__init__.py
deailab/tests/test_handlers.py
deailab/tests/test_jobmanager.py
deailab-0.1.11.data/data/etc/jupyter/jupyter_notebook_config.d/deailab.json
deailab-0.1.11.data/data/etc/jupyter/jupyter_server_config.d/deailab.json
deailab-0.1.11.data/data/share/jupyter/labextensions/deailab/package.json
deailab-0.1.11.data/data/share/jupyter/labextensions/deailab/static/122.b7d35f9cacb613c84d5c.js
deailab-0.1.11.data/data/share/jupyter/labextensions/deailab/static/140.911efce90534acdae904.js
deailab-0.1.11.data/data/share/jupyter/labextensions/deailab/static/140.911efce90534acdae904.js.LICENSE.txt
deailab-0.1.11.data/data/share/jupyter/labextensions/deailab/static/171.8cd16469e21f38378094.js
deailab-0.1.11.data/data/share/jupyter/labextensions/deailab/static/242.a0c4cad6ba78754edf09.js
deailab-0.1.11.data/data/share/jupyter/labextensions/deailab/static/282.a6e215a085cdaeb6e19c.js
deailab-0.1.11.data/data/share/jupyter/labextensions/deailab/static/338.6de1963f1e0e9a2a6bf8.js
deailab-0.1.11.data/data/share/jupyter/labextensions/deailab/static/338.6de1963f1e0e9a2a6bf8.js.LICENSE.txt
deailab-0.1.11.data/data/share/jupyter/labextensions/deailab/static/378.30785e73af188c899359.js
deailab-0.1.11.data/data/share/jupyter/labextensions/deailab/static/426.8f16fc61416dd2b8c550.js
deailab-0.1.11.data/data/share/jupyter/labextensions/deailab/static/470.bbb513f17262856ba896.js
deailab-0.1.11.data/data/share/jupyter/labextensions/deailab/static/470.bbb513f17262856ba896.js.LICENSE.txt
deailab-0.1.11.data/data/share/jupyter/labextensions/deailab/static/570.553c7a3d7341bba91395.js
deailab-0.1.11.data/data/share/jupyter/labextensions/deailab/static/66.547c9e549a51c7b1b4d8.js
deailab-0.1.11.data/data/share/jupyter/labextensions/deailab/static/66.547c9e549a51c7b1b4d8.js.LICENSE.txt
deailab-0.1.11.dist-info/METADATA
deailab-0.1.11.dist-info/WHEEL
deailab-0.1.11.dist-info/licenses/LICENSE
deailab-0.1.11.dist-info/RECORD
