Metadata-Version: 2.1
Name: deailab
Version: 0.1.11
Summary: A JupyterLab extension for DeAI.
Project-URL: Homepage, https://github.com/0011ai/deailab
Project-URL: Bug Tracker, https://github.com/0011ai/deailab/issues
Project-URL: Repository, https://github.com/0011ai/deailab.git
Author-email: Maarten Ectors <maarten@0011.ai>
License: Copyright 2023 Profit Growing Innovator LTD
License-File: LICENSE
Classifier: Framework :: Jupyter
Classifier: Framework :: Jupyter :: JupyterLab
Classifier: Framework :: Jupyter :: JupyterLab :: 4
Classifier: Framework :: Jupyter :: JupyterLab :: Extensions
Classifier: Framework :: Jupyter :: JupyterLab :: Extensions :: Prebuilt
Classifier: License :: OSI Approved :: MIT License
Classifier: Programming Language :: Python
Classifier: Programming Language :: Python :: 3
Classifier: Programming Language :: Python :: 3.8
Classifier: Programming Language :: Python :: 3.9
Classifier: Programming Language :: Python :: 3.10
Classifier: Programming Language :: Python :: 3.11
Requires-Python: >=3.8
Requires-Dist: deairequest
Requires-Dist: jupyter-server<3,>=2.0.1
Provides-Extra: test
Requires-Dist: bacalhau-sdk; extra == 'test'
Requires-Dist: cerberus; extra == 'test'
Requires-Dist: coverage; extra == 'test'
Requires-Dist: ipfshttpclient; extra == 'test'
Requires-Dist: jupytext; extra == 'test'
Requires-Dist: pipreqs; extra == 'test'
Requires-Dist: pytest; extra == 'test'
Requires-Dist: pytest-asyncio; extra == 'test'
Requires-Dist: pytest-cov; extra == 'test'
Requires-Dist: pytest-jupyter[server]>=0.6.0; extra == 'test'
Requires-Dist: pytest-mock; extra == 'test'
Requires-Dist: python-box; extra == 'test'
